crawlab/__init__.py
crawlab/auth_token.py
crawlab/constants.py
crawlab/log.py
crawlab/logger.py
crawlab/result.py
crawlab/actions/__init__.py
crawlab/actions/login.py
crawlab/actions/migrate.py
crawlab/actions/migrate_no_upgrade.py
crawlab/actions/upload.py
crawlab/cli/__init__.py
crawlab/cli/main.py
crawlab/cli/actions/__init__.py
crawlab/cli/actions/config.py
crawlab/cli/actions/login.py
crawlab/cli/actions/migrate.py
crawlab/cli/actions/upload.py
crawlab/client/__init__.py
crawlab/client/client.py
crawlab/client/request.py
crawlab/client/response.py
crawlab/config/__init__.py
crawlab/config/config.py
crawlab/config/spider.py
crawlab/config/task.py
crawlab/constants/__init__.py
crawlab/constants/request.py
crawlab/constants/upload.py
crawlab/entity/__init__.py
crawlab/entity/address.py
crawlab/entity/result.py
crawlab/entity/task.py
crawlab/errors/__init__.py
crawlab/errors/upload.py
crawlab/grpc/__init__.py
crawlab/grpc/entity/__init__.py
crawlab/grpc/entity/node_info_pb2.py
crawlab/grpc/entity/node_info_pb2_grpc.py
crawlab/grpc/entity/plugin_request_pb2.py
crawlab/grpc/entity/plugin_request_pb2_grpc.py
crawlab/grpc/entity/request_pb2.py
crawlab/grpc/entity/request_pb2_grpc.py
crawlab/grpc/entity/response_code_pb2.py
crawlab/grpc/entity/response_code_pb2_grpc.py
crawlab/grpc/entity/response_pb2.py
crawlab/grpc/entity/response_pb2_grpc.py
crawlab/grpc/entity/stream_message_code_pb2.py
crawlab/grpc/entity/stream_message_code_pb2_grpc.py
crawlab/grpc/entity/stream_message_data_task_pb2.py
crawlab/grpc/entity/stream_message_data_task_pb2_grpc.py
crawlab/grpc/entity/stream_message_pb2.py
crawlab/grpc/entity/stream_message_pb2_grpc.py
crawlab/grpc/models/__init__.py
crawlab/grpc/models/node_pb2.py
crawlab/grpc/models/node_pb2_grpc.py
crawlab/grpc/models/task_pb2.py
crawlab/grpc/models/task_pb2_grpc.py
crawlab/grpc/services/__init__.py
crawlab/grpc/services/message_service_pb2.py
crawlab/grpc/services/message_service_pb2_grpc.py
crawlab_sdk-0.6.2.dist-info/METADATA
crawlab_sdk-0.6.2.dist-info/WHEEL
crawlab_sdk-0.6.2.dist-info/entry_points.txt
crawlab_sdk-0.6.2.dist-info/top_level.txt
crawlab_sdk-0.6.2.dist-info/RECORD
