Metadata-Version: 2.1
Name: crawlab-sdk
Version: 0.6.2
Summary: Python SDK for Crawlab
Home-page: https://github.com/crawlab-team/crawlab-sdk
Author: tikazyq
Author-email: tikazyq@163.com
License: BSD-3-Clause
Classifier: Programming Language :: Python :: 3
Classifier: License :: OSI Approved :: BSD License
Classifier: Operating System :: OS Independent
Requires-Dist: requests (>=2.27)
Requires-Dist: pathspec (==0.8.0)
Requires-Dist: grpcio (>=1.53.1)
Requires-Dist: grpcio-tools (>=1.51.1)
Requires-Dist: grpc-interceptor-headers (==0.1.0)
Requires-Dist: print-color (==0.4.5)
Requires-Dist: pyyaml (==6.0)
Requires-Dist: pymongo (>=4)
